COPYING.txt
MANIFEST.in
README.txt
setup.py
cpruntime/__init__.py
cpruntime/cpruntime.py
cpruntime.egg-info/PKG-INFO
cpruntime.egg-info/SOURCES.txt
cpruntime.egg-info/dependency_links.txt
cpruntime.egg-info/top_level.txt