Metadata-Version: 1.0
Name: cpruntime
Version: 0.0.7
Summary: python module for cloudpi
Home-page: https://github.com/lipengyuntian
Author: py.li
Author-email: py.li@samsung.com
License: UNKNOWN
Platform: UNKNOWN
Classifier: Programming Language :: Python
Classifier: Programming Language :: Python :: 2
Classifier: License :: OSI Approved :: GNU General Public License (GPL)
Classifier: Operating System :: OS Independent
Classifier: Development Status :: 1 - Planning
Classifier: Environment :: Console
Classifier: Intended Audience :: Science/Research
Classifier: Topic :: Scientific/Engineering :: GIS
